just_bash/__init__.py
just_bash/bash.py
just_bash/py.typed
just_bash/types.py
just_bash/ast/__init__.py
just_bash/ast/factory.py
just_bash/ast/types.py
just_bash/commands/__init__.py
just_bash/commands/registry.py
just_bash/commands/argv/__init__.py
just_bash/commands/argv/argv.py
just_bash/commands/awk/__init__.py
just_bash/commands/awk/awk.py
just_bash/commands/base64/__init__.py
just_bash/commands/base64/base64.py
just_bash/commands/basename/__init__.py
just_bash/commands/basename/basename.py
just_bash/commands/bash/__init__.py
just_bash/commands/bash/bash.py
just_bash/commands/cat/__init__.py
just_bash/commands/cat/cat.py
just_bash/commands/checksum/__init__.py
just_bash/commands/checksum/checksum.py
just_bash/commands/chmod/__init__.py
just_bash/commands/chmod/chmod.py
just_bash/commands/column/__init__.py
just_bash/commands/column/column.py
just_bash/commands/comm/__init__.py
just_bash/commands/comm/comm.py
just_bash/commands/compression/__init__.py
just_bash/commands/compression/compression.py
just_bash/commands/cp/__init__.py
just_bash/commands/cp/cp.py
just_bash/commands/curl/__init__.py
just_bash/commands/curl/curl.py
just_bash/commands/cut/__init__.py
just_bash/commands/cut/cut.py
just_bash/commands/date/__init__.py
just_bash/commands/date/date.py
just_bash/commands/diff/__init__.py
just_bash/commands/diff/diff.py
just_bash/commands/dirname/__init__.py
just_bash/commands/dirname/dirname.py
just_bash/commands/du/__init__.py
just_bash/commands/du/du.py
just_bash/commands/echo/__init__.py
just_bash/commands/echo/echo.py
just_bash/commands/env/__init__.py
just_bash/commands/env/env.py
just_bash/commands/expand/__init__.py
just_bash/commands/expand/expand.py
just_bash/commands/expr/__init__.py
just_bash/commands/expr/expr.py
just_bash/commands/file/__init__.py
just_bash/commands/file/file.py
just_bash/commands/find/__init__.py
just_bash/commands/find/find.py
just_bash/commands/fold/__init__.py
just_bash/commands/fold/fold.py
just_bash-0.1.9.dist-info/METADATA
just_bash-0.1.9.dist-info/WHEEL
just_bash-0.1.9.dist-info/RECORD
