Metadata-Version: 2.4
Name: just-bash
Version: 0.1.9
Summary: A pure Python bash interpreter with in-memory virtual filesystem
Project-URL: Homepage, https://github.com/dbreunig/just-bash-py
Project-URL: Repository, https://github.com/dbreunig/just-bash-py
Author: Drew Breunig
License-Expression: Apache-2.0
Keywords: bash,interpreter,sandbox,shell,virtual-filesystem
Classifier: Development Status :: 3 - Alpha
Classifier: Intended Audience :: Developers
Classifier: License :: OSI Approved :: Apache Software License
Classifier: Programming Language :: Python :: 3
Classifier: Programming Language :: Python :: 3.11
Classifier: Programming Language :: Python :: 3.12
Classifier: Programming Language :: Python :: 3.13
Classifier: Topic :: Software Development :: Interpreters
Classifier: Typing :: Typed
Requires-Python: >=3.11
Requires-Dist: aiofiles>=23.0
Requires-Dist: aiohttp>=3.9
Requires-Dist: markdownify>=0.11
Requires-Dist: nest-asyncio>=1.5
Provides-Extra: dev
Requires-Dist: mypy>=1.8; extra == 'dev'
Requires-Dist: pytest-asyncio>=0.23; extra == 'dev'
Requires-Dist: pytest>=8.0; extra == 'dev'
Requires-Dist: ruff>=0.1; extra == 'dev'
